{
  "artists": {
    "title": "Artistas (Por Scrobbles)",
    "data": {
      "The Beatles": 2125,
      "Porcupine Tree": 1448,
      "Radiohead": 1349,
      "Steven Wilson": 1262,
      "Anathema": 1065,
      "Riverside": 1053,
      "Alcest": 1022,
      "Pink Floyd": 976,
      "Sigur Rós": 966,
      "The Cure": 814,
      "David Bowie": 714,
      "Tool": 690,
      "Bob Dylan": 681,
      "M83": 668,
      "The Beach Boys": 660
    },
    "total": 15493,
    "details": {
      "The Beatles": {
        "user_count": 2,
        "total_scrobbles": 2125,
        "shared_users": [
          "Nubis84",
          "paqueradejere"
        ],
        "user_plays": {},
        "artist": "",
        "album": "",
        "track": ""
      },
      "Porcupine Tree": {
        "user_count": 2,
        "total_scrobbles": 1448,
        "shared_users": [
          "Nubis84",
          "paqueradejere"
        ],
        "user_plays": {},
        "artist": "",
        "album": "",
        "track": ""
      },
      "Radiohead": {
        "user_count": 2,
        "total_scrobbles": 1349,
        "shared_users": [
          "Nubis84",
          "paqueradejere"
        ],
        "user_plays": {},
        "artist": "",
        "album": "",
        "track": ""
      },
      "Steven Wilson": {
        "user_count": 2,
        "total_scrobbles": 1262,
        "shared_users": [
          "Nubis84",
          "paqueradejere"
        ],
        "user_plays": {},
        "artist": "",
        "album": "",
        "track": ""
      },
      "Anathema": {
        "user_count": 1,
        "total_scrobbles": 1065,
        "shared_users": [
          "Nubis84"
        ],
        "user_plays": {},
        "artist": "",
        "album": "",
        "track": ""
      },
      "Riverside": {
        "user_count": 1,
        "total_scrobbles": 1053,
        "shared_users": [
          "Nubis84"
        ],
        "user_plays": {},
        "artist": "",
        "album": "",
        "track": ""
      },
      "Alcest": {
        "user_count": 2,
        "total_scrobbles": 1022,
        "shared_users": [
          "Nubis84",
          "paqueradejere"
        ],
        "user_plays": {},
        "artist": "",
        "album": "",
        "track": ""
      },
      "Pink Floyd": {
        "user_count": 2,
        "total_scrobbles": 976,
        "shared_users": [
          "Nubis84",
          "paqueradejere"
        ],
        "user_plays": {},
        "artist": "",
        "album": "",
        "track": ""
      },
      "Sigur Rós": {
        "user_count": 2,
        "total_scrobbles": 966,
        "shared_users": [
          "Nubis84",
          "paqueradejere"
        ],
        "user_plays": {},
        "artist": "",
        "album": "",
        "track": ""
      },
      "The Cure": {
        "user_count": 2,
        "total_scrobbles": 814,
        "shared_users": [
          "Nubis84",
          "paqueradejere"
        ],
        "user_plays": {},
        "artist": "",
        "album": "",
        "track": ""
      },
      "David Bowie": {
        "user_count": 2,
        "total_scrobbles": 714,
        "shared_users": [
          "Nubis84",
          "paqueradejere"
        ],
        "user_plays": {},
        "artist": "",
        "album": "",
        "track": ""
      },
      "Tool": {
        "user_count": 2,
        "total_scrobbles": 690,
        "shared_users": [
          "Nubis84",
          "paqueradejere"
        ],
        "user_plays": {},
        "artist": "",
        "album": "",
        "track": ""
      },
      "Bob Dylan": {
        "user_count": 1,
        "total_scrobbles": 681,
        "shared_users": [
          "Nubis84"
        ],
        "user_plays": {},
        "artist": "",
        "album": "",
        "track": ""
      },
      "M83": {
        "user_count": 2,
        "total_scrobbles": 668,
        "shared_users": [
          "Nubis84",
          "paqueradejere"
        ],
        "user_plays": {},
        "artist": "",
        "album": "",
        "track": ""
      },
      "The Beach Boys": {
        "user_count": 2,
        "total_scrobbles": 660,
        "shared_users": [
          "Nubis84",
          "paqueradejere"
        ],
        "user_plays": {},
        "artist": "",
        "album": "",
        "track": ""
      }
    },
    "type": "scrobbles"
  },
  "albums": {
    "title": "Álbumes (Por Scrobbles)",
    "data": {
      "Have a Nice Life - Deathconsciousness": 236,
      "Anathema - Weather Systems": 232,
      "David Bowie - The Rise and Fall of Ziggy Stardust and the Spiders From Mars": 224,
      "The Cure - Disintegration": 219,
      "Porcupine Tree - In Absentia": 208,
      "Toby Fox - Undertale": 193,
      "Radiohead - OK Computer": 192,
      "Bon Iver - For Emma, Forever Ago": 186,
      "Radiohead - In Rainbows": 181,
      "Alcest - Souvenirs d'un autre monde": 180,
      "Radiohead - Kid A": 178,
      "Blackfield - Welcome to My DNA": 177,
      "A Winged Victory for the Sullen - A Winged Victory for the Sullen": 172,
      "PJ Harvey - Stories From the City, Stories From the Sea": 168,
      "The Beach Boys - Pet Sounds": 168
    },
    "total": 2914,
    "details": {
      "Have a Nice Life - Deathconsciousness": {
        "user_count": 2,
        "total_scrobbles": 236,
        "shared_users": [
          "Nubis84",
          "paqueradejere"
        ],
        "user_plays": {},
        "artist": "Have a Nice Life",
        "album": "Deathconsciousness",
        "track": ""
      },
      "Anathema - Weather Systems": {
        "user_count": 1,
        "total_scrobbles": 232,
        "shared_users": [
          "Nubis84"
        ],
        "user_plays": {},
        "artist": "Anathema",
        "album": "Weather Systems",
        "track": ""
      },
      "David Bowie - The Rise and Fall of Ziggy Stardust and the Spiders From Mars": {
        "user_count": 2,
        "total_scrobbles": 224,
        "shared_users": [
          "Nubis84",
          "paqueradejere"
        ],
        "user_plays": {},
        "artist": "David Bowie",
        "album": "The Rise and Fall of Ziggy Stardust and the Spiders From Mars",
        "track": ""
      },
      "The Cure - Disintegration": {
        "user_count": 2,
        "total_scrobbles": 219,
        "shared_users": [
          "Nubis84",
          "paqueradejere"
        ],
        "user_plays": {},
        "artist": "The Cure",
        "album": "Disintegration",
        "track": ""
      },
      "Porcupine Tree - In Absentia": {
        "user_count": 2,
        "total_scrobbles": 208,
        "shared_users": [
          "Nubis84",
          "paqueradejere"
        ],
        "user_plays": {},
        "artist": "Porcupine Tree",
        "album": "In Absentia",
        "track": ""
      },
      "Toby Fox - Undertale": {
        "user_count": 1,
        "total_scrobbles": 193,
        "shared_users": [
          "Nubis84"
        ],
        "user_plays": {},
        "artist": "Toby Fox",
        "album": "Undertale",
        "track": ""
      },
      "Radiohead - OK Computer": {
        "user_count": 1,
        "total_scrobbles": 192,
        "shared_users": [
          "Nubis84"
        ],
        "user_plays": {},
        "artist": "Radiohead",
        "album": "OK Computer",
        "track": ""
      },
      "Bon Iver - For Emma, Forever Ago": {
        "user_count": 1,
        "total_scrobbles": 186,
        "shared_users": [
          "Nubis84"
        ],
        "user_plays": {},
        "artist": "Bon Iver",
        "album": "For Emma, Forever Ago",
        "track": ""
      },
      "Radiohead - In Rainbows": {
        "user_count": 2,
        "total_scrobbles": 181,
        "shared_users": [
          "Nubis84",
          "paqueradejere"
        ],
        "user_plays": {},
        "artist": "Radiohead",
        "album": "In Rainbows",
        "track": ""
      },
      "Alcest - Souvenirs d'un autre monde": {
        "user_count": 1,
        "total_scrobbles": 180,
        "shared_users": [
          "Nubis84"
        ],
        "user_plays": {},
        "artist": "Alcest",
        "album": "Souvenirs d'un autre monde",
        "track": ""
      },
      "Radiohead - Kid A": {
        "user_count": 1,
        "total_scrobbles": 178,
        "shared_users": [
          "Nubis84"
        ],
        "user_plays": {},
        "artist": "Radiohead",
        "album": "Kid A",
        "track": ""
      },
      "Blackfield - Welcome to My DNA": {
        "user_count": 1,
        "total_scrobbles": 177,
        "shared_users": [
          "Nubis84"
        ],
        "user_plays": {},
        "artist": "Blackfield",
        "album": "Welcome to My DNA",
        "track": ""
      },
      "A Winged Victory for the Sullen - A Winged Victory for the Sullen": {
        "user_count": 1,
        "total_scrobbles": 172,
        "shared_users": [
          "Nubis84"
        ],
        "user_plays": {},
        "artist": "A Winged Victory for the Sullen",
        "album": "A Winged Victory for the Sullen",
        "track": ""
      },
      "PJ Harvey - Stories From the City, Stories From the Sea": {
        "user_count": 2,
        "total_scrobbles": 168,
        "shared_users": [
          "Nubis84",
          "paqueradejere"
        ],
        "user_plays": {},
        "artist": "PJ Harvey",
        "album": "Stories From the City, Stories From the Sea",
        "track": ""
      },
      "The Beach Boys - Pet Sounds": {
        "user_count": 2,
        "total_scrobbles": 168,
        "shared_users": [
          "Nubis84",
          "paqueradejere"
        ],
        "user_plays": {},
        "artist": "The Beach Boys",
        "album": "Pet Sounds",
        "track": ""
      }
    },
    "type": "scrobbles"
  },
  "tracks": {
    "title": "Canciones (Por Scrobbles)",
    "data": {
      "Alcest - Souvenirs d'un autre monde": 100,
      "M83 - Midnight City": 91,
      "The Cure - Pictures of You": 91,
      "Deep Purple - Child in Time": 82,
      "Riverside - Conceiving You": 80,
      "Porcupine Tree - Trains": 79,
      "Sigur Rós - Hoppípolla": 76,
      "Coldplay - Yellow": 69,
      "Radiohead - Fake Plastic Trees": 69,
      "Black Sabbath - Paranoid": 67,
      "Pixies - Monkey Gone to Heaven": 66,
      "Portishead - Roads": 66,
      "Alcest - Autre Temps": 65,
      "Porcupine Tree - The Start of Something Beautiful": 64,
      "Arcade Fire - Ready to Start": 63
    },
    "total": 1128,
    "details": {
      "Alcest - Souvenirs d'un autre monde": {
        "user_count": 1,
        "total_scrobbles": 100,
        "shared_users": [
          "Nubis84"
        ],
        "user_plays": {},
        "artist": "Alcest",
        "album": "",
        "track": "Souvenirs d'un autre monde"
      },
      "M83 - Midnight City": {
        "user_count": 1,
        "total_scrobbles": 91,
        "shared_users": [
          "Nubis84"
        ],
        "user_plays": {},
        "artist": "M83",
        "album": "",
        "track": "Midnight City"
      },
      "The Cure - Pictures of You": {
        "user_count": 2,
        "total_scrobbles": 91,
        "shared_users": [
          "Nubis84",
          "paqueradejere"
        ],
        "user_plays": {},
        "artist": "The Cure",
        "album": "",
        "track": "Pictures of You"
      },
      "Deep Purple - Child in Time": {
        "user_count": 1,
        "total_scrobbles": 82,
        "shared_users": [
          "Nubis84"
        ],
        "user_plays": {},
        "artist": "Deep Purple",
        "album": "",
        "track": "Child in Time"
      },
      "Riverside - Conceiving You": {
        "user_count": 1,
        "total_scrobbles": 80,
        "shared_users": [
          "Nubis84"
        ],
        "user_plays": {},
        "artist": "Riverside",
        "album": "",
        "track": "Conceiving You"
      },
      "Porcupine Tree - Trains": {
        "user_count": 1,
        "total_scrobbles": 79,
        "shared_users": [
          "Nubis84"
        ],
        "user_plays": {},
        "artist": "Porcupine Tree",
        "album": "",
        "track": "Trains"
      },
      "Sigur Rós - Hoppípolla": {
        "user_count": 2,
        "total_scrobbles": 76,
        "shared_users": [
          "Nubis84",
          "paqueradejere"
        ],
        "user_plays": {},
        "artist": "Sigur Rós",
        "album": "",
        "track": "Hoppípolla"
      },
      "Coldplay - Yellow": {
        "user_count": 1,
        "total_scrobbles": 69,
        "shared_users": [
          "Nubis84"
        ],
        "user_plays": {},
        "artist": "Coldplay",
        "album": "",
        "track": "Yellow"
      },
      "Radiohead - Fake Plastic Trees": {
        "user_count": 1,
        "total_scrobbles": 69,
        "shared_users": [
          "Nubis84"
        ],
        "user_plays": {},
        "artist": "Radiohead",
        "album": "",
        "track": "Fake Plastic Trees"
      },
      "Black Sabbath - Paranoid": {
        "user_count": 2,
        "total_scrobbles": 67,
        "shared_users": [
          "Nubis84",
          "paqueradejere"
        ],
        "user_plays": {},
        "artist": "Black Sabbath",
        "album": "",
        "track": "Paranoid"
      },
      "Pixies - Monkey Gone to Heaven": {
        "user_count": 1,
        "total_scrobbles": 66,
        "shared_users": [
          "Nubis84"
        ],
        "user_plays": {},
        "artist": "Pixies",
        "album": "",
        "track": "Monkey Gone to Heaven"
      },
      "Portishead - Roads": {
        "user_count": 1,
        "total_scrobbles": 66,
        "shared_users": [
          "Nubis84"
        ],
        "user_plays": {},
        "artist": "Portishead",
        "album": "",
        "track": "Roads"
      },
      "Alcest - Autre Temps": {
        "user_count": 2,
        "total_scrobbles": 65,
        "shared_users": [
          "Nubis84",
          "paqueradejere"
        ],
        "user_plays": {},
        "artist": "Alcest",
        "album": "",
        "track": "Autre Temps"
      },
      "Porcupine Tree - The Start of Something Beautiful": {
        "user_count": 1,
        "total_scrobbles": 64,
        "shared_users": [
          "Nubis84"
        ],
        "user_plays": {},
        "artist": "Porcupine Tree",
        "album": "",
        "track": "The Start of Something Beautiful"
      },
      "Arcade Fire - Ready to Start": {
        "user_count": 1,
        "total_scrobbles": 63,
        "shared_users": [
          "Nubis84"
        ],
        "user_plays": {},
        "artist": "Arcade Fire",
        "album": "",
        "track": "Ready to Start"
      }
    },
    "type": "scrobbles"
  },
  "genres": {
    "title": "Géneros (Por Scrobbles)",
    "data": {
      "electronic": 6798,
      "ambient": 6295,
      "post-rock": 3994,
      "rock": 3955,
      "experimental": 3288,
      "instrumental": 3266,
      "singer-songwriter": 3134,
      "indie": 3045,
      "jazz": 2721,
      "folk": 2597,
      "pop": 2401,
      "Progressive rock": 2380,
      "classic rock": 2154,
      "female vocalists": 2123,
      "shoegaze": 2063
    },
    "total": 50214,
    "details": {
      "electronic": {
        "user_count": 2,
        "total_scrobbles": 6798,
        "shared_users": [
          "paqueradejere",
          "Nubis84"
        ],
        "user_plays": {},
        "artist": "",
        "album": "",
        "track": ""
      },
      "ambient": {
        "user_count": 2,
        "total_scrobbles": 6295,
        "shared_users": [
          "paqueradejere",
          "Nubis84"
        ],
        "user_plays": {},
        "artist": "",
        "album": "",
        "track": ""
      },
      "post-rock": {
        "user_count": 2,
        "total_scrobbles": 3994,
        "shared_users": [
          "paqueradejere",
          "Nubis84"
        ],
        "user_plays": {},
        "artist": "",
        "album": "",
        "track": ""
      },
      "rock": {
        "user_count": 2,
        "total_scrobbles": 3955,
        "shared_users": [
          "paqueradejere",
          "Nubis84"
        ],
        "user_plays": {},
        "artist": "",
        "album": "",
        "track": ""
      },
      "experimental": {
        "user_count": 2,
        "total_scrobbles": 3288,
        "shared_users": [
          "paqueradejere",
          "Nubis84"
        ],
        "user_plays": {},
        "artist": "",
        "album": "",
        "track": ""
      },
      "instrumental": {
        "user_count": 2,
        "total_scrobbles": 3266,
        "shared_users": [
          "paqueradejere",
          "Nubis84"
        ],
        "user_plays": {},
        "artist": "",
        "album": "",
        "track": ""
      },
      "singer-songwriter": {
        "user_count": 2,
        "total_scrobbles": 3134,
        "shared_users": [
          "paqueradejere",
          "Nubis84"
        ],
        "user_plays": {},
        "artist": "",
        "album": "",
        "track": ""
      },
      "indie": {
        "user_count": 2,
        "total_scrobbles": 3045,
        "shared_users": [
          "paqueradejere",
          "Nubis84"
        ],
        "user_plays": {},
        "artist": "",
        "album": "",
        "track": ""
      },
      "jazz": {
        "user_count": 2,
        "total_scrobbles": 2721,
        "shared_users": [
          "paqueradejere",
          "Nubis84"
        ],
        "user_plays": {},
        "artist": "",
        "album": "",
        "track": ""
      },
      "folk": {
        "user_count": 2,
        "total_scrobbles": 2597,
        "shared_users": [
          "paqueradejere",
          "Nubis84"
        ],
        "user_plays": {},
        "artist": "",
        "album": "",
        "track": ""
      },
      "pop": {
        "user_count": 2,
        "total_scrobbles": 2401,
        "shared_users": [
          "paqueradejere",
          "Nubis84"
        ],
        "user_plays": {},
        "artist": "",
        "album": "",
        "track": ""
      },
      "Progressive rock": {
        "user_count": 2,
        "total_scrobbles": 2380,
        "shared_users": [
          "paqueradejere",
          "Nubis84"
        ],
        "user_plays": {},
        "artist": "",
        "album": "",
        "track": ""
      },
      "classic rock": {
        "user_count": 2,
        "total_scrobbles": 2154,
        "shared_users": [
          "paqueradejere",
          "Nubis84"
        ],
        "user_plays": {},
        "artist": "",
        "album": "",
        "track": ""
      },
      "female vocalists": {
        "user_count": 2,
        "total_scrobbles": 2123,
        "shared_users": [
          "paqueradejere",
          "Nubis84"
        ],
        "user_plays": {},
        "artist": "",
        "album": "",
        "track": ""
      },
      "shoegaze": {
        "user_count": 2,
        "total_scrobbles": 2063,
        "shared_users": [
          "paqueradejere",
          "Nubis84"
        ],
        "user_plays": {},
        "artist": "",
        "album": "",
        "track": ""
      }
    },
    "type": "scrobbles"
  },
  "labels": {
    "title": "Sellos (Por Scrobbles)",
    "data": {
      "Columbia": 720,
      "Warner Bros. Records": 613,
      "Parlophone": 567,
      "[no label]": 561,
      "Erased Tapes Records": 385,
      "Kscope": 356,
      "Atlantic": 339,
      "Jagjaguwar": 274,
      "EMI": 252,
      "Epic": 242,
      "Enemies List": 238,
      "Reprise Records": 233,
      "Capitol Records": 233,
      "4AD": 215,
      "Apple Records": 208
    },
    "total": 5436,
    "details": {
      "Columbia": {
        "user_count": 2,
        "total_scrobbles": 720,
        "shared_users": [
          "Nubis84",
          "paqueradejere"
        ],
        "user_plays": {},
        "artist": "",
        "album": "",
        "track": ""
      },
      "Warner Bros. Records": {
        "user_count": 2,
        "total_scrobbles": 613,
        "shared_users": [
          "Nubis84",
          "paqueradejere"
        ],
        "user_plays": {},
        "artist": "",
        "album": "",
        "track": ""
      },
      "Parlophone": {
        "user_count": 2,
        "total_scrobbles": 567,
        "shared_users": [
          "Nubis84",
          "paqueradejere"
        ],
        "user_plays": {},
        "artist": "",
        "album": "",
        "track": ""
      },
      "[no label]": {
        "user_count": 2,
        "total_scrobbles": 561,
        "shared_users": [
          "Nubis84",
          "paqueradejere"
        ],
        "user_plays": {},
        "artist": "",
        "album": "",
        "track": ""
      },
      "Erased Tapes Records": {
        "user_count": 2,
        "total_scrobbles": 385,
        "shared_users": [
          "Nubis84",
          "paqueradejere"
        ],
        "user_plays": {},
        "artist": "",
        "album": "",
        "track": ""
      },
      "Kscope": {
        "user_count": 1,
        "total_scrobbles": 356,
        "shared_users": [
          "Nubis84"
        ],
        "user_plays": {},
        "artist": "",
        "album": "",
        "track": ""
      },
      "Atlantic": {
        "user_count": 2,
        "total_scrobbles": 339,
        "shared_users": [
          "Nubis84",
          "paqueradejere"
        ],
        "user_plays": {},
        "artist": "",
        "album": "",
        "track": ""
      },
      "Jagjaguwar": {
        "user_count": 2,
        "total_scrobbles": 274,
        "shared_users": [
          "Nubis84",
          "paqueradejere"
        ],
        "user_plays": {},
        "artist": "",
        "album": "",
        "track": ""
      },
      "EMI": {
        "user_count": 2,
        "total_scrobbles": 252,
        "shared_users": [
          "Nubis84",
          "paqueradejere"
        ],
        "user_plays": {},
        "artist": "",
        "album": "",
        "track": ""
      },
      "Epic": {
        "user_count": 2,
        "total_scrobbles": 242,
        "shared_users": [
          "Nubis84",
          "paqueradejere"
        ],
        "user_plays": {},
        "artist": "",
        "album": "",
        "track": ""
      },
      "Enemies List": {
        "user_count": 2,
        "total_scrobbles": 238,
        "shared_users": [
          "Nubis84",
          "paqueradejere"
        ],
        "user_plays": {},
        "artist": "",
        "album": "",
        "track": ""
      },
      "Reprise Records": {
        "user_count": 2,
        "total_scrobbles": 233,
        "shared_users": [
          "Nubis84",
          "paqueradejere"
        ],
        "user_plays": {},
        "artist": "",
        "album": "",
        "track": ""
      },
      "Capitol Records": {
        "user_count": 2,
        "total_scrobbles": 233,
        "shared_users": [
          "Nubis84",
          "paqueradejere"
        ],
        "user_plays": {},
        "artist": "",
        "album": "",
        "track": ""
      },
      "4AD": {
        "user_count": 2,
        "total_scrobbles": 215,
        "shared_users": [
          "Nubis84",
          "paqueradejere"
        ],
        "user_plays": {},
        "artist": "",
        "album": "",
        "track": ""
      },
      "Apple Records": {
        "user_count": 1,
        "total_scrobbles": 208,
        "shared_users": [
          "Nubis84"
        ],
        "user_plays": {},
        "artist": "",
        "album": "",
        "track": ""
      }
    },
    "type": "scrobbles"
  },
  "release_years": {
    "title": "Años de Lanzamiento (Por Scrobbles)",
    "data": {
      "2017": 1574,
      "2018": 1450,
      "2016": 1285,
      "2015": 1251,
      "2009": 1228,
      "2011": 1181,
      "2019": 1173,
      "2012": 1146,
      "2010": 1140,
      "2006": 1113,
      "2014": 1109,
      "2008": 1033,
      "2007": 1025,
      "2021": 924,
      "2004": 921
    },
    "total": 17553,
    "details": {
      "2017": {
        "user_count": 2,
        "total_scrobbles": 1574,
        "shared_users": [
          "paqueradejere",
          "Nubis84"
        ],
        "user_plays": {},
        "artist": "",
        "album": "",
        "track": ""
      },
      "2018": {
        "user_count": 2,
        "total_scrobbles": 1450,
        "shared_users": [
          "paqueradejere",
          "Nubis84"
        ],
        "user_plays": {},
        "artist": "",
        "album": "",
        "track": ""
      },
      "2016": {
        "user_count": 2,
        "total_scrobbles": 1285,
        "shared_users": [
          "paqueradejere",
          "Nubis84"
        ],
        "user_plays": {},
        "artist": "",
        "album": "",
        "track": ""
      },
      "2015": {
        "user_count": 2,
        "total_scrobbles": 1251,
        "shared_users": [
          "paqueradejere",
          "Nubis84"
        ],
        "user_plays": {},
        "artist": "",
        "album": "",
        "track": ""
      },
      "2009": {
        "user_count": 2,
        "total_scrobbles": 1228,
        "shared_users": [
          "paqueradejere",
          "Nubis84"
        ],
        "user_plays": {},
        "artist": "",
        "album": "",
        "track": ""
      },
      "2011": {
        "user_count": 2,
        "total_scrobbles": 1181,
        "shared_users": [
          "paqueradejere",
          "Nubis84"
        ],
        "user_plays": {},
        "artist": "",
        "album": "",
        "track": ""
      },
      "2019": {
        "user_count": 2,
        "total_scrobbles": 1173,
        "shared_users": [
          "paqueradejere",
          "Nubis84"
        ],
        "user_plays": {},
        "artist": "",
        "album": "",
        "track": ""
      },
      "2012": {
        "user_count": 2,
        "total_scrobbles": 1146,
        "shared_users": [
          "paqueradejere",
          "Nubis84"
        ],
        "user_plays": {},
        "artist": "",
        "album": "",
        "track": ""
      },
      "2010": {
        "user_count": 2,
        "total_scrobbles": 1140,
        "shared_users": [
          "paqueradejere",
          "Nubis84"
        ],
        "user_plays": {},
        "artist": "",
        "album": "",
        "track": ""
      },
      "2006": {
        "user_count": 2,
        "total_scrobbles": 1113,
        "shared_users": [
          "paqueradejere",
          "Nubis84"
        ],
        "user_plays": {},
        "artist": "",
        "album": "",
        "track": ""
      },
      "2014": {
        "user_count": 2,
        "total_scrobbles": 1109,
        "shared_users": [
          "paqueradejere",
          "Nubis84"
        ],
        "user_plays": {},
        "artist": "",
        "album": "",
        "track": ""
      },
      "2008": {
        "user_count": 2,
        "total_scrobbles": 1033,
        "shared_users": [
          "paqueradejere",
          "Nubis84"
        ],
        "user_plays": {},
        "artist": "",
        "album": "",
        "track": ""
      },
      "2007": {
        "user_count": 2,
        "total_scrobbles": 1025,
        "shared_users": [
          "paqueradejere",
          "Nubis84"
        ],
        "user_plays": {},
        "artist": "",
        "album": "",
        "track": ""
      },
      "2021": {
        "user_count": 2,
        "total_scrobbles": 924,
        "shared_users": [
          "paqueradejere",
          "Nubis84"
        ],
        "user_plays": {},
        "artist": "",
        "album": "",
        "track": ""
      },
      "2004": {
        "user_count": 2,
        "total_scrobbles": 921,
        "shared_users": [
          "paqueradejere",
          "Nubis84"
        ],
        "user_plays": {},
        "artist": "",
        "album": "",
        "track": ""
      }
    },
    "type": "scrobbles"
  },
  "all_combined": {
    "title": "Top 15 Global por Scrobbles",
    "data": {
      "Release_years: 2010s": 12199,
      "Release_years: 2000s": 8014,
      "Genres: electronic": 6798,
      "Genres: ambient": 6295,
      "Release_years: 2020s+": 4615,
      "Genres: post-rock": 3994,
      "Genres: rock": 3955,
      "Genres: experimental": 3288,
      "Release_years: 1990s": 3202,
      "Artists: The Beatles": 2125,
      "Artists: Porcupine Tree": 1448,
      "Artists: Radiohead": 1349,
      "Release_years: 1980s": 1308,
      "Artists: Steven Wilson": 1262,
      "Artists: Anathema": 1065
    },
    "total": 60917,
    "details": {
      "Release_years: 2010s": {
        "original_name": "2010s",
        "category": "release_years",
        "user_count": 2,
        "total_scrobbles": 12199,
        "shared_users": [
          "paqueradejere",
          "Nubis84"
        ]
      },
      "Release_years: 2000s": {
        "original_name": "2000s",
        "category": "release_years",
        "user_count": 2,
        "total_scrobbles": 8014,
        "shared_users": [
          "paqueradejere",
          "Nubis84"
        ]
      },
      "Genres: electronic": {
        "original_name": "electronic",
        "category": "genres",
        "user_count": 2,
        "total_scrobbles": 6798,
        "shared_users": [
          "paqueradejere",
          "Nubis84"
        ]
      },
      "Genres: ambient": {
        "original_name": "ambient",
        "category": "genres",
        "user_count": 2,
        "total_scrobbles": 6295,
        "shared_users": [
          "paqueradejere",
          "Nubis84"
        ]
      },
      "Release_years: 2020s+": {
        "original_name": "2020s+",
        "category": "release_years",
        "user_count": 2,
        "total_scrobbles": 4615,
        "shared_users": [
          "paqueradejere",
          "Nubis84"
        ]
      },
      "Genres: post-rock": {
        "original_name": "post-rock",
        "category": "genres",
        "user_count": 2,
        "total_scrobbles": 3994,
        "shared_users": [
          "paqueradejere",
          "Nubis84"
        ]
      },
      "Genres: rock": {
        "original_name": "rock",
        "category": "genres",
        "user_count": 2,
        "total_scrobbles": 3955,
        "shared_users": [
          "paqueradejere",
          "Nubis84"
        ]
      },
      "Genres: experimental": {
        "original_name": "experimental",
        "category": "genres",
        "user_count": 2,
        "total_scrobbles": 3288,
        "shared_users": [
          "paqueradejere",
          "Nubis84"
        ]
      },
      "Release_years: 1990s": {
        "original_name": "1990s",
        "category": "release_years",
        "user_count": 2,
        "total_scrobbles": 3202,
        "shared_users": [
          "paqueradejere",
          "Nubis84"
        ]
      },
      "Artists: The Beatles": {
        "original_name": "The Beatles",
        "category": "artists",
        "user_count": 2,
        "total_scrobbles": 2125,
        "shared_users": [
          "Nubis84",
          "paqueradejere"
        ]
      },
      "Artists: Porcupine Tree": {
        "original_name": "Porcupine Tree",
        "category": "artists",
        "user_count": 2,
        "total_scrobbles": 1448,
        "shared_users": [
          "Nubis84",
          "paqueradejere"
        ]
      },
      "Artists: Radiohead": {
        "original_name": "Radiohead",
        "category": "artists",
        "user_count": 2,
        "total_scrobbles": 1349,
        "shared_users": [
          "Nubis84",
          "paqueradejere"
        ]
      },
      "Release_years: 1980s": {
        "original_name": "1980s",
        "category": "release_years",
        "user_count": 2,
        "total_scrobbles": 1308,
        "shared_users": [
          "paqueradejere",
          "Nubis84"
        ]
      },
      "Artists: Steven Wilson": {
        "original_name": "Steven Wilson",
        "category": "artists",
        "user_count": 2,
        "total_scrobbles": 1262,
        "shared_users": [
          "Nubis84",
          "paqueradejere"
        ]
      },
      "Artists: Anathema": {
        "original_name": "Anathema",
        "category": "artists",
        "user_count": 1,
        "total_scrobbles": 1065,
        "shared_users": [
          "Nubis84"
        ]
      }
    },
    "type": "combined"
  }
}