{
  "artists": {
    "title": "Artistas (Por Scrobbles)",
    "data": {
      "Lana Del Rey": 2757,
      "The Cure": 2661,
      "Radiohead": 2180,
      "Pink Floyd": 2078,
      "The Beatles": 1874,
      "Röyksopp": 1448,
      "Cocteau Twins": 1409,
      "Beach House": 1391,
      "IDLES": 1362,
      "Björk": 1156,
      "Eartheater": 1111,
      "Slowdive": 1091,
      "The Chemical Brothers": 1088,
      "The Smiths": 1083,
      "Arca": 1066
    },
    "total": 23755,
    "details": {
      "Lana Del Rey": {
        "user_count": 4,
        "total_scrobbles": 2757,
        "shared_users": [
          "Frikomid",
          "Nubis84",
          "Rocky_stereo",
          "sdecandelario"
        ],
        "user_plays": {},
        "artist": "",
        "album": "",
        "track": ""
      },
      "The Cure": {
        "user_count": 4,
        "total_scrobbles": 2661,
        "shared_users": [
          "Frikomid",
          "Nubis84",
          "Rocky_stereo",
          "sdecandelario"
        ],
        "user_plays": {},
        "artist": "",
        "album": "",
        "track": ""
      },
      "Radiohead": {
        "user_count": 4,
        "total_scrobbles": 2180,
        "shared_users": [
          "Frikomid",
          "Nubis84",
          "Rocky_stereo",
          "sdecandelario"
        ],
        "user_plays": {},
        "artist": "",
        "album": "",
        "track": ""
      },
      "Pink Floyd": {
        "user_count": 4,
        "total_scrobbles": 2078,
        "shared_users": [
          "Frikomid",
          "Nubis84",
          "Rocky_stereo",
          "sdecandelario"
        ],
        "user_plays": {},
        "artist": "",
        "album": "",
        "track": ""
      },
      "The Beatles": {
        "user_count": 4,
        "total_scrobbles": 1874,
        "shared_users": [
          "Frikomid",
          "Nubis84",
          "Rocky_stereo",
          "sdecandelario"
        ],
        "user_plays": {},
        "artist": "",
        "album": "",
        "track": ""
      },
      "Röyksopp": {
        "user_count": 4,
        "total_scrobbles": 1448,
        "shared_users": [
          "Frikomid",
          "Nubis84",
          "Rocky_stereo",
          "sdecandelario"
        ],
        "user_plays": {},
        "artist": "",
        "album": "",
        "track": ""
      },
      "Cocteau Twins": {
        "user_count": 4,
        "total_scrobbles": 1409,
        "shared_users": [
          "Frikomid",
          "Nubis84",
          "Rocky_stereo",
          "sdecandelario"
        ],
        "user_plays": {},
        "artist": "",
        "album": "",
        "track": ""
      },
      "Beach House": {
        "user_count": 4,
        "total_scrobbles": 1391,
        "shared_users": [
          "Frikomid",
          "Nubis84",
          "Rocky_stereo",
          "sdecandelario"
        ],
        "user_plays": {},
        "artist": "",
        "album": "",
        "track": ""
      },
      "IDLES": {
        "user_count": 3,
        "total_scrobbles": 1362,
        "shared_users": [
          "Frikomid",
          "Nubis84",
          "sdecandelario"
        ],
        "user_plays": {},
        "artist": "",
        "album": "",
        "track": ""
      },
      "Björk": {
        "user_count": 4,
        "total_scrobbles": 1156,
        "shared_users": [
          "Frikomid",
          "Nubis84",
          "Rocky_stereo",
          "sdecandelario"
        ],
        "user_plays": {},
        "artist": "",
        "album": "",
        "track": ""
      },
      "Eartheater": {
        "user_count": 3,
        "total_scrobbles": 1111,
        "shared_users": [
          "Frikomid",
          "Nubis84",
          "sdecandelario"
        ],
        "user_plays": {},
        "artist": "",
        "album": "",
        "track": ""
      },
      "Slowdive": {
        "user_count": 4,
        "total_scrobbles": 1091,
        "shared_users": [
          "Frikomid",
          "Nubis84",
          "Rocky_stereo",
          "sdecandelario"
        ],
        "user_plays": {},
        "artist": "",
        "album": "",
        "track": ""
      },
      "The Chemical Brothers": {
        "user_count": 3,
        "total_scrobbles": 1088,
        "shared_users": [
          "Frikomid",
          "Nubis84",
          "sdecandelario"
        ],
        "user_plays": {},
        "artist": "",
        "album": "",
        "track": ""
      },
      "The Smiths": {
        "user_count": 4,
        "total_scrobbles": 1083,
        "shared_users": [
          "Frikomid",
          "Nubis84",
          "Rocky_stereo",
          "sdecandelario"
        ],
        "user_plays": {},
        "artist": "",
        "album": "",
        "track": ""
      },
      "Arca": {
        "user_count": 4,
        "total_scrobbles": 1066,
        "shared_users": [
          "Frikomid",
          "Nubis84",
          "Rocky_stereo",
          "sdecandelario"
        ],
        "user_plays": {},
        "artist": "",
        "album": "",
        "track": ""
      }
    },
    "type": "scrobbles"
  },
  "albums": {
    "title": "Álbumes (Por Scrobbles)",
    "data": {
      "Radiohead - In Rainbows": 628,
      "Eartheater - Phoenix: Flames Are Dew Upon My Skin": 590,
      "Guerreros Del Bajo - Dos Mil Siempre": 535,
      "Pink Floyd - The Dark Side of the Moon": 523,
      "Slowdive - Souvlaki": 512,
      "The Strokes - The New Abnormal": 457,
      "Lana Del Rey - Blue Banisters": 443,
      "Sol Seppy - The Bells Of 1 2": 419,
      "Have a Nice Life - Deathconsciousness": 416,
      "Lana Del Rey - Norman Fucking Rockwell!": 407,
      "my bloody valentine - Loveless": 406,
      "Pescado Rabioso - Artaud": 405,
      "Turnstile - GLOW ON": 400,
      "Beach House - Once Twice Melody": 394,
      "Candy Claws - Ceres & Calypso in the Deep Time": 393
    },
    "total": 6928,
    "details": {
      "Radiohead - In Rainbows": {
        "user_count": 4,
        "total_scrobbles": 628,
        "shared_users": [
          "Frikomid",
          "Nubis84",
          "Rocky_stereo",
          "sdecandelario"
        ],
        "user_plays": {},
        "artist": "Radiohead",
        "album": "In Rainbows",
        "track": ""
      },
      "Eartheater - Phoenix: Flames Are Dew Upon My Skin": {
        "user_count": 1,
        "total_scrobbles": 590,
        "shared_users": [
          "Frikomid"
        ],
        "user_plays": {},
        "artist": "Eartheater",
        "album": "Phoenix: Flames Are Dew Upon My Skin",
        "track": ""
      },
      "Guerreros Del Bajo - Dos Mil Siempre": {
        "user_count": 1,
        "total_scrobbles": 535,
        "shared_users": [
          "Rocky_stereo"
        ],
        "user_plays": {},
        "artist": "Guerreros Del Bajo",
        "album": "Dos Mil Siempre",
        "track": ""
      },
      "Pink Floyd - The Dark Side of the Moon": {
        "user_count": 3,
        "total_scrobbles": 523,
        "shared_users": [
          "Nubis84",
          "Rocky_stereo",
          "sdecandelario"
        ],
        "user_plays": {},
        "artist": "Pink Floyd",
        "album": "The Dark Side of the Moon",
        "track": ""
      },
      "Slowdive - Souvlaki": {
        "user_count": 4,
        "total_scrobbles": 512,
        "shared_users": [
          "Frikomid",
          "Nubis84",
          "Rocky_stereo",
          "sdecandelario"
        ],
        "user_plays": {},
        "artist": "Slowdive",
        "album": "Souvlaki",
        "track": ""
      },
      "The Strokes - The New Abnormal": {
        "user_count": 4,
        "total_scrobbles": 457,
        "shared_users": [
          "Frikomid",
          "Nubis84",
          "Rocky_stereo",
          "sdecandelario"
        ],
        "user_plays": {},
        "artist": "The Strokes",
        "album": "The New Abnormal",
        "track": ""
      },
      "Lana Del Rey - Blue Banisters": {
        "user_count": 2,
        "total_scrobbles": 443,
        "shared_users": [
          "Frikomid",
          "Rocky_stereo"
        ],
        "user_plays": {},
        "artist": "Lana Del Rey",
        "album": "Blue Banisters",
        "track": ""
      },
      "Sol Seppy - The Bells Of 1 2": {
        "user_count": 1,
        "total_scrobbles": 419,
        "shared_users": [
          "Frikomid"
        ],
        "user_plays": {},
        "artist": "Sol Seppy",
        "album": "The Bells Of 1 2",
        "track": ""
      },
      "Have a Nice Life - Deathconsciousness": {
        "user_count": 4,
        "total_scrobbles": 416,
        "shared_users": [
          "Frikomid",
          "Nubis84",
          "Rocky_stereo",
          "sdecandelario"
        ],
        "user_plays": {},
        "artist": "Have a Nice Life",
        "album": "Deathconsciousness",
        "track": ""
      },
      "Lana Del Rey - Norman Fucking Rockwell!": {
        "user_count": 3,
        "total_scrobbles": 407,
        "shared_users": [
          "Frikomid",
          "Rocky_stereo",
          "sdecandelario"
        ],
        "user_plays": {},
        "artist": "Lana Del Rey",
        "album": "Norman Fucking Rockwell!",
        "track": ""
      },
      "my bloody valentine - Loveless": {
        "user_count": 4,
        "total_scrobbles": 406,
        "shared_users": [
          "Frikomid",
          "Nubis84",
          "Rocky_stereo",
          "sdecandelario"
        ],
        "user_plays": {},
        "artist": "my bloody valentine",
        "album": "Loveless",
        "track": ""
      },
      "Pescado Rabioso - Artaud": {
        "user_count": 3,
        "total_scrobbles": 405,
        "shared_users": [
          "Frikomid",
          "Rocky_stereo",
          "sdecandelario"
        ],
        "user_plays": {},
        "artist": "Pescado Rabioso",
        "album": "Artaud",
        "track": ""
      },
      "Turnstile - GLOW ON": {
        "user_count": 2,
        "total_scrobbles": 400,
        "shared_users": [
          "Rocky_stereo",
          "sdecandelario"
        ],
        "user_plays": {},
        "artist": "Turnstile",
        "album": "GLOW ON",
        "track": ""
      },
      "Beach House - Once Twice Melody": {
        "user_count": 2,
        "total_scrobbles": 394,
        "shared_users": [
          "Frikomid",
          "Rocky_stereo"
        ],
        "user_plays": {},
        "artist": "Beach House",
        "album": "Once Twice Melody",
        "track": ""
      },
      "Candy Claws - Ceres & Calypso in the Deep Time": {
        "user_count": 4,
        "total_scrobbles": 393,
        "shared_users": [
          "Frikomid",
          "Nubis84",
          "Rocky_stereo",
          "sdecandelario"
        ],
        "user_plays": {},
        "artist": "Candy Claws",
        "album": "Ceres & Calypso in the Deep Time",
        "track": ""
      }
    },
    "type": "scrobbles"
  },
  "tracks": {
    "title": "Canciones (Por Scrobbles)",
    "data": {
      "Paavoharju - Haihtuu": 202,
      "Eartheater - How To Fight": 198,
      "Aurora - Giving In to the Love": 164,
      "Charli xcx - Good Ones": 163,
      "Sol Seppy - Move": 163,
      "Laghonia - My Love": 161,
      "Danny L Harle - Ashes of Love (feat. Caroline Polachek)": 155,
      "Siouxsie and the Banshees - Dazzle": 155,
      "Jonathan Bree - No Reminders": 154,
      "The Cure - Lovesong": 150,
      "POLIÇA - Madness (feat. Tim Fain)": 148,
      "Meg Baird & Mary Lattimore - Painter of Tygers": 144,
      "Portishead - The Rip": 142,
      "The Cure - Just Like Heaven": 142,
      "Porches - rangerover": 141
    },
    "total": 2382,
    "details": {
      "Paavoharju - Haihtuu": {
        "user_count": 1,
        "total_scrobbles": 202,
        "shared_users": [
          "Frikomid"
        ],
        "user_plays": {},
        "artist": "Paavoharju",
        "album": "",
        "track": "Haihtuu"
      },
      "Eartheater - How To Fight": {
        "user_count": 1,
        "total_scrobbles": 198,
        "shared_users": [
          "Frikomid"
        ],
        "user_plays": {},
        "artist": "Eartheater",
        "album": "",
        "track": "How To Fight"
      },
      "Aurora - Giving In to the Love": {
        "user_count": 1,
        "total_scrobbles": 164,
        "shared_users": [
          "Frikomid"
        ],
        "user_plays": {},
        "artist": "Aurora",
        "album": "",
        "track": "Giving In to the Love"
      },
      "Charli xcx - Good Ones": {
        "user_count": 1,
        "total_scrobbles": 163,
        "shared_users": [
          "Frikomid"
        ],
        "user_plays": {},
        "artist": "Charli xcx",
        "album": "",
        "track": "Good Ones"
      },
      "Sol Seppy - Move": {
        "user_count": 1,
        "total_scrobbles": 163,
        "shared_users": [
          "Frikomid"
        ],
        "user_plays": {},
        "artist": "Sol Seppy",
        "album": "",
        "track": "Move"
      },
      "Laghonia - My Love": {
        "user_count": 2,
        "total_scrobbles": 161,
        "shared_users": [
          "Frikomid",
          "Rocky_stereo"
        ],
        "user_plays": {},
        "artist": "Laghonia",
        "album": "",
        "track": "My Love"
      },
      "Danny L Harle - Ashes of Love (feat. Caroline Polachek)": {
        "user_count": 1,
        "total_scrobbles": 155,
        "shared_users": [
          "Frikomid"
        ],
        "user_plays": {},
        "artist": "Danny L Harle",
        "album": "",
        "track": "Ashes of Love (feat. Caroline Polachek)"
      },
      "Siouxsie and the Banshees - Dazzle": {
        "user_count": 2,
        "total_scrobbles": 155,
        "shared_users": [
          "Frikomid",
          "sdecandelario"
        ],
        "user_plays": {},
        "artist": "Siouxsie and the Banshees",
        "album": "",
        "track": "Dazzle"
      },
      "Jonathan Bree - No Reminders": {
        "user_count": 1,
        "total_scrobbles": 154,
        "shared_users": [
          "Frikomid"
        ],
        "user_plays": {},
        "artist": "Jonathan Bree",
        "album": "",
        "track": "No Reminders"
      },
      "The Cure - Lovesong": {
        "user_count": 4,
        "total_scrobbles": 150,
        "shared_users": [
          "Frikomid",
          "Nubis84",
          "Rocky_stereo",
          "sdecandelario"
        ],
        "user_plays": {},
        "artist": "The Cure",
        "album": "",
        "track": "Lovesong"
      },
      "POLIÇA - Madness (feat. Tim Fain)": {
        "user_count": 1,
        "total_scrobbles": 148,
        "shared_users": [
          "Frikomid"
        ],
        "user_plays": {},
        "artist": "POLIÇA",
        "album": "",
        "track": "Madness (feat. Tim Fain)"
      },
      "Meg Baird & Mary Lattimore - Painter of Tygers": {
        "user_count": 1,
        "total_scrobbles": 144,
        "shared_users": [
          "Frikomid"
        ],
        "user_plays": {},
        "artist": "Meg Baird & Mary Lattimore",
        "album": "",
        "track": "Painter of Tygers"
      },
      "Portishead - The Rip": {
        "user_count": 3,
        "total_scrobbles": 142,
        "shared_users": [
          "Frikomid",
          "Nubis84",
          "sdecandelario"
        ],
        "user_plays": {},
        "artist": "Portishead",
        "album": "",
        "track": "The Rip"
      },
      "The Cure - Just Like Heaven": {
        "user_count": 3,
        "total_scrobbles": 142,
        "shared_users": [
          "Nubis84",
          "Rocky_stereo",
          "sdecandelario"
        ],
        "user_plays": {},
        "artist": "The Cure",
        "album": "",
        "track": "Just Like Heaven"
      },
      "Porches - rangerover": {
        "user_count": 1,
        "total_scrobbles": 141,
        "shared_users": [
          "Frikomid"
        ],
        "user_plays": {},
        "artist": "Porches",
        "album": "",
        "track": "rangerover"
      }
    },
    "type": "scrobbles"
  },
  "genres": {
    "title": "Géneros (Por Scrobbles)",
    "data": {
      "indie": 14740,
      "electronic": 14379,
      "pop": 12202,
      "female vocalists": 11611,
      "post-punk": 9737,
      "indie pop": 9297,
      "rock": 7952,
      "folk": 6571,
      "experimental": 5337,
      "punk": 5064,
      "indie rock": 4985,
      "singer-songwriter": 4948,
      "new wave": 4252,
      "spanish": 3965,
      "dream pop": 3950
    },
    "total": 118990,
    "details": {
      "indie": {
        "user_count": 4,
        "total_scrobbles": 14740,
        "shared_users": [
          "Frikomid",
          "sdecandelario",
          "Nubis84",
          "Rocky_stereo"
        ],
        "user_plays": {},
        "artist": "",
        "album": "",
        "track": ""
      },
      "electronic": {
        "user_count": 4,
        "total_scrobbles": 14379,
        "shared_users": [
          "Frikomid",
          "sdecandelario",
          "Nubis84",
          "Rocky_stereo"
        ],
        "user_plays": {},
        "artist": "",
        "album": "",
        "track": ""
      },
      "pop": {
        "user_count": 4,
        "total_scrobbles": 12202,
        "shared_users": [
          "sdecandelario",
          "Frikomid",
          "Nubis84",
          "Rocky_stereo"
        ],
        "user_plays": {},
        "artist": "",
        "album": "",
        "track": ""
      },
      "female vocalists": {
        "user_count": 4,
        "total_scrobbles": 11611,
        "shared_users": [
          "sdecandelario",
          "Frikomid",
          "Nubis84",
          "Rocky_stereo"
        ],
        "user_plays": {},
        "artist": "",
        "album": "",
        "track": ""
      },
      "post-punk": {
        "user_count": 4,
        "total_scrobbles": 9737,
        "shared_users": [
          "Nubis84",
          "Frikomid",
          "sdecandelario",
          "Rocky_stereo"
        ],
        "user_plays": {},
        "artist": "",
        "album": "",
        "track": ""
      },
      "indie pop": {
        "user_count": 4,
        "total_scrobbles": 9297,
        "shared_users": [
          "sdecandelario",
          "Frikomid",
          "Nubis84",
          "Rocky_stereo"
        ],
        "user_plays": {},
        "artist": "",
        "album": "",
        "track": ""
      },
      "rock": {
        "user_count": 4,
        "total_scrobbles": 7952,
        "shared_users": [
          "Frikomid",
          "sdecandelario",
          "Nubis84",
          "Rocky_stereo"
        ],
        "user_plays": {},
        "artist": "",
        "album": "",
        "track": ""
      },
      "folk": {
        "user_count": 4,
        "total_scrobbles": 6571,
        "shared_users": [
          "sdecandelario",
          "Frikomid",
          "Nubis84",
          "Rocky_stereo"
        ],
        "user_plays": {},
        "artist": "",
        "album": "",
        "track": ""
      },
      "experimental": {
        "user_count": 4,
        "total_scrobbles": 5337,
        "shared_users": [
          "sdecandelario",
          "Frikomid",
          "Nubis84",
          "Rocky_stereo"
        ],
        "user_plays": {},
        "artist": "",
        "album": "",
        "track": ""
      },
      "punk": {
        "user_count": 4,
        "total_scrobbles": 5064,
        "shared_users": [
          "Frikomid",
          "sdecandelario",
          "Nubis84",
          "Rocky_stereo"
        ],
        "user_plays": {},
        "artist": "",
        "album": "",
        "track": ""
      },
      "indie rock": {
        "user_count": 4,
        "total_scrobbles": 4985,
        "shared_users": [
          "sdecandelario",
          "Frikomid",
          "Nubis84",
          "Rocky_stereo"
        ],
        "user_plays": {},
        "artist": "",
        "album": "",
        "track": ""
      },
      "singer-songwriter": {
        "user_count": 4,
        "total_scrobbles": 4948,
        "shared_users": [
          "sdecandelario",
          "Frikomid",
          "Nubis84",
          "Rocky_stereo"
        ],
        "user_plays": {},
        "artist": "",
        "album": "",
        "track": ""
      },
      "new wave": {
        "user_count": 4,
        "total_scrobbles": 4252,
        "shared_users": [
          "Frikomid",
          "sdecandelario",
          "Nubis84",
          "Rocky_stereo"
        ],
        "user_plays": {},
        "artist": "",
        "album": "",
        "track": ""
      },
      "spanish": {
        "user_count": 4,
        "total_scrobbles": 3965,
        "shared_users": [
          "sdecandelario",
          "Frikomid",
          "Nubis84",
          "Rocky_stereo"
        ],
        "user_plays": {},
        "artist": "",
        "album": "",
        "track": ""
      },
      "dream pop": {
        "user_count": 4,
        "total_scrobbles": 3950,
        "shared_users": [
          "Nubis84",
          "Frikomid",
          "sdecandelario",
          "Rocky_stereo"
        ],
        "user_plays": {},
        "artist": "",
        "album": "",
        "track": ""
      }
    },
    "type": "scrobbles"
  },
  "labels": {
    "title": "Sellos (Por Scrobbles)",
    "data": {
      "[no label]": 1973,
      "Interscope Records": 1903,
      "Columbia": 1543,
      "Polydor": 1037,
      "Parlophone": 1001,
      "4AD": 860,
      "Sub Pop Records": 847,
      "EMI": 834,
      "Partisan Records": 727,
      "XL Recordings": 718,
      "Atlantic": 660,
      "Rough Trade": 586,
      "Microfon": 571,
      "Sony Music": 544,
      "Ninja Tune": 540
    },
    "total": 14344,
    "details": {
      "[no label]": {
        "user_count": 4,
        "total_scrobbles": 1973,
        "shared_users": [
          "Frikomid",
          "Nubis84",
          "Rocky_stereo",
          "sdecandelario"
        ],
        "user_plays": {},
        "artist": "",
        "album": "",
        "track": ""
      },
      "Interscope Records": {
        "user_count": 4,
        "total_scrobbles": 1903,
        "shared_users": [
          "Frikomid",
          "Nubis84",
          "Rocky_stereo",
          "sdecandelario"
        ],
        "user_plays": {},
        "artist": "",
        "album": "",
        "track": ""
      },
      "Columbia": {
        "user_count": 4,
        "total_scrobbles": 1543,
        "shared_users": [
          "Frikomid",
          "Nubis84",
          "Rocky_stereo",
          "sdecandelario"
        ],
        "user_plays": {},
        "artist": "",
        "album": "",
        "track": ""
      },
      "Polydor": {
        "user_count": 4,
        "total_scrobbles": 1037,
        "shared_users": [
          "Frikomid",
          "Nubis84",
          "Rocky_stereo",
          "sdecandelario"
        ],
        "user_plays": {},
        "artist": "",
        "album": "",
        "track": ""
      },
      "Parlophone": {
        "user_count": 4,
        "total_scrobbles": 1001,
        "shared_users": [
          "Frikomid",
          "Nubis84",
          "Rocky_stereo",
          "sdecandelario"
        ],
        "user_plays": {},
        "artist": "",
        "album": "",
        "track": ""
      },
      "4AD": {
        "user_count": 4,
        "total_scrobbles": 860,
        "shared_users": [
          "Frikomid",
          "Nubis84",
          "Rocky_stereo",
          "sdecandelario"
        ],
        "user_plays": {},
        "artist": "",
        "album": "",
        "track": ""
      },
      "Sub Pop Records": {
        "user_count": 4,
        "total_scrobbles": 847,
        "shared_users": [
          "Frikomid",
          "Nubis84",
          "Rocky_stereo",
          "sdecandelario"
        ],
        "user_plays": {},
        "artist": "",
        "album": "",
        "track": ""
      },
      "EMI": {
        "user_count": 4,
        "total_scrobbles": 834,
        "shared_users": [
          "Frikomid",
          "Nubis84",
          "Rocky_stereo",
          "sdecandelario"
        ],
        "user_plays": {},
        "artist": "",
        "album": "",
        "track": ""
      },
      "Partisan Records": {
        "user_count": 4,
        "total_scrobbles": 727,
        "shared_users": [
          "Frikomid",
          "Nubis84",
          "Rocky_stereo",
          "sdecandelario"
        ],
        "user_plays": {},
        "artist": "",
        "album": "",
        "track": ""
      },
      "XL Recordings": {
        "user_count": 4,
        "total_scrobbles": 718,
        "shared_users": [
          "Frikomid",
          "Nubis84",
          "Rocky_stereo",
          "sdecandelario"
        ],
        "user_plays": {},
        "artist": "",
        "album": "",
        "track": ""
      },
      "Atlantic": {
        "user_count": 4,
        "total_scrobbles": 660,
        "shared_users": [
          "Frikomid",
          "Nubis84",
          "Rocky_stereo",
          "sdecandelario"
        ],
        "user_plays": {},
        "artist": "",
        "album": "",
        "track": ""
      },
      "Rough Trade": {
        "user_count": 4,
        "total_scrobbles": 586,
        "shared_users": [
          "Frikomid",
          "Nubis84",
          "Rocky_stereo",
          "sdecandelario"
        ],
        "user_plays": {},
        "artist": "",
        "album": "",
        "track": ""
      },
      "Microfon": {
        "user_count": 4,
        "total_scrobbles": 571,
        "shared_users": [
          "Frikomid",
          "Nubis84",
          "Rocky_stereo",
          "sdecandelario"
        ],
        "user_plays": {},
        "artist": "",
        "album": "",
        "track": ""
      },
      "Sony Music": {
        "user_count": 4,
        "total_scrobbles": 544,
        "shared_users": [
          "Frikomid",
          "Nubis84",
          "Rocky_stereo",
          "sdecandelario"
        ],
        "user_plays": {},
        "artist": "",
        "album": "",
        "track": ""
      },
      "Ninja Tune": {
        "user_count": 4,
        "total_scrobbles": 540,
        "shared_users": [
          "Frikomid",
          "Nubis84",
          "Rocky_stereo",
          "sdecandelario"
        ],
        "user_plays": {},
        "artist": "",
        "album": "",
        "track": ""
      }
    },
    "type": "scrobbles"
  },
  "release_years": {
    "title": "Años de Lanzamiento (Por Scrobbles)",
    "data": {
      "2020": 7093,
      "2021": 5892,
      "2022": 5209,
      "2023": 4148,
      "2019": 3784,
      "2017": 3271,
      "2024": 3252,
      "2018": 2945,
      "2013": 2885,
      "2015": 2817,
      "2016": 2778,
      "2025": 2639,
      "2014": 2559,
      "2008": 2024,
      "2012": 2020
    },
    "total": 53316,
    "details": {
      "2020": {
        "user_count": 4,
        "total_scrobbles": 7093,
        "shared_users": [
          "sdecandelario",
          "Frikomid",
          "Nubis84",
          "Rocky_stereo"
        ],
        "user_plays": {},
        "artist": "",
        "album": "",
        "track": ""
      },
      "2021": {
        "user_count": 4,
        "total_scrobbles": 5892,
        "shared_users": [
          "sdecandelario",
          "Frikomid",
          "Nubis84",
          "Rocky_stereo"
        ],
        "user_plays": {},
        "artist": "",
        "album": "",
        "track": ""
      },
      "2022": {
        "user_count": 4,
        "total_scrobbles": 5209,
        "shared_users": [
          "sdecandelario",
          "Frikomid",
          "Nubis84",
          "Rocky_stereo"
        ],
        "user_plays": {},
        "artist": "",
        "album": "",
        "track": ""
      },
      "2023": {
        "user_count": 4,
        "total_scrobbles": 4148,
        "shared_users": [
          "sdecandelario",
          "Frikomid",
          "Nubis84",
          "Rocky_stereo"
        ],
        "user_plays": {},
        "artist": "",
        "album": "",
        "track": ""
      },
      "2019": {
        "user_count": 4,
        "total_scrobbles": 3784,
        "shared_users": [
          "sdecandelario",
          "Frikomid",
          "Nubis84",
          "Rocky_stereo"
        ],
        "user_plays": {},
        "artist": "",
        "album": "",
        "track": ""
      },
      "2017": {
        "user_count": 4,
        "total_scrobbles": 3271,
        "shared_users": [
          "sdecandelario",
          "Frikomid",
          "Nubis84",
          "Rocky_stereo"
        ],
        "user_plays": {},
        "artist": "",
        "album": "",
        "track": ""
      },
      "2024": {
        "user_count": 4,
        "total_scrobbles": 3252,
        "shared_users": [
          "sdecandelario",
          "Frikomid",
          "Nubis84",
          "Rocky_stereo"
        ],
        "user_plays": {},
        "artist": "",
        "album": "",
        "track": ""
      },
      "2018": {
        "user_count": 4,
        "total_scrobbles": 2945,
        "shared_users": [
          "sdecandelario",
          "Frikomid",
          "Nubis84",
          "Rocky_stereo"
        ],
        "user_plays": {},
        "artist": "",
        "album": "",
        "track": ""
      },
      "2013": {
        "user_count": 4,
        "total_scrobbles": 2885,
        "shared_users": [
          "sdecandelario",
          "Frikomid",
          "Nubis84",
          "Rocky_stereo"
        ],
        "user_plays": {},
        "artist": "",
        "album": "",
        "track": ""
      },
      "2015": {
        "user_count": 4,
        "total_scrobbles": 2817,
        "shared_users": [
          "sdecandelario",
          "Frikomid",
          "Nubis84",
          "Rocky_stereo"
        ],
        "user_plays": {},
        "artist": "",
        "album": "",
        "track": ""
      },
      "2016": {
        "user_count": 4,
        "total_scrobbles": 2778,
        "shared_users": [
          "sdecandelario",
          "Frikomid",
          "Nubis84",
          "Rocky_stereo"
        ],
        "user_plays": {},
        "artist": "",
        "album": "",
        "track": ""
      },
      "2025": {
        "user_count": 4,
        "total_scrobbles": 2639,
        "shared_users": [
          "sdecandelario",
          "Frikomid",
          "Nubis84",
          "Rocky_stereo"
        ],
        "user_plays": {},
        "artist": "",
        "album": "",
        "track": ""
      },
      "2014": {
        "user_count": 4,
        "total_scrobbles": 2559,
        "shared_users": [
          "sdecandelario",
          "Frikomid",
          "Nubis84",
          "Rocky_stereo"
        ],
        "user_plays": {},
        "artist": "",
        "album": "",
        "track": ""
      },
      "2008": {
        "user_count": 4,
        "total_scrobbles": 2024,
        "shared_users": [
          "sdecandelario",
          "Frikomid",
          "Nubis84",
          "Rocky_stereo"
        ],
        "user_plays": {},
        "artist": "",
        "album": "",
        "track": ""
      },
      "2012": {
        "user_count": 4,
        "total_scrobbles": 2020,
        "shared_users": [
          "sdecandelario",
          "Frikomid",
          "Nubis84",
          "Rocky_stereo"
        ],
        "user_plays": {},
        "artist": "",
        "album": "",
        "track": ""
      }
    },
    "type": "scrobbles"
  },
  "all_combined": {
    "title": "Top 15 Global por Scrobbles",
    "data": {
      "Release_years: 2020s+": 28233,
      "Release_years: 2010s": 26246,
      "Genres: indie": 14740,
      "Genres: electronic": 14379,
      "Genres: pop": 12202,
      "Genres: female vocalists": 11611,
      "Release_years: 2000s": 11409,
      "Genres: post-punk": 9737,
      "Release_years: 1990s": 6808,
      "Release_years: 1980s": 3422,
      "Artists: Lana Del Rey": 2757,
      "Artists: The Cure": 2661,
      "Artists: Radiohead": 2180,
      "Artists: Pink Floyd": 2078,
      "Labels: [no label]": 1973
    },
    "total": 150436,
    "details": {
      "Release_years: 2020s+": {
        "original_name": "2020s+",
        "category": "release_years",
        "user_count": 4,
        "total_scrobbles": 28233,
        "shared_users": [
          "sdecandelario",
          "Frikomid",
          "Nubis84",
          "Rocky_stereo"
        ]
      },
      "Release_years: 2010s": {
        "original_name": "2010s",
        "category": "release_years",
        "user_count": 4,
        "total_scrobbles": 26246,
        "shared_users": [
          "sdecandelario",
          "Frikomid",
          "Nubis84",
          "Rocky_stereo"
        ]
      },
      "Genres: indie": {
        "original_name": "indie",
        "category": "genres",
        "user_count": 4,
        "total_scrobbles": 14740,
        "shared_users": [
          "Frikomid",
          "sdecandelario",
          "Nubis84",
          "Rocky_stereo"
        ]
      },
      "Genres: electronic": {
        "original_name": "electronic",
        "category": "genres",
        "user_count": 4,
        "total_scrobbles": 14379,
        "shared_users": [
          "Frikomid",
          "sdecandelario",
          "Nubis84",
          "Rocky_stereo"
        ]
      },
      "Genres: pop": {
        "original_name": "pop",
        "category": "genres",
        "user_count": 4,
        "total_scrobbles": 12202,
        "shared_users": [
          "sdecandelario",
          "Frikomid",
          "Nubis84",
          "Rocky_stereo"
        ]
      },
      "Genres: female vocalists": {
        "original_name": "female vocalists",
        "category": "genres",
        "user_count": 4,
        "total_scrobbles": 11611,
        "shared_users": [
          "sdecandelario",
          "Frikomid",
          "Nubis84",
          "Rocky_stereo"
        ]
      },
      "Release_years: 2000s": {
        "original_name": "2000s",
        "category": "release_years",
        "user_count": 4,
        "total_scrobbles": 11409,
        "shared_users": [
          "sdecandelario",
          "Frikomid",
          "Nubis84",
          "Rocky_stereo"
        ]
      },
      "Genres: post-punk": {
        "original_name": "post-punk",
        "category": "genres",
        "user_count": 4,
        "total_scrobbles": 9737,
        "shared_users": [
          "Nubis84",
          "Frikomid",
          "sdecandelario",
          "Rocky_stereo"
        ]
      },
      "Release_years: 1990s": {
        "original_name": "1990s",
        "category": "release_years",
        "user_count": 4,
        "total_scrobbles": 6808,
        "shared_users": [
          "sdecandelario",
          "Frikomid",
          "Nubis84",
          "Rocky_stereo"
        ]
      },
      "Release_years: 1980s": {
        "original_name": "1980s",
        "category": "release_years",
        "user_count": 4,
        "total_scrobbles": 3422,
        "shared_users": [
          "sdecandelario",
          "Frikomid",
          "Nubis84",
          "Rocky_stereo"
        ]
      },
      "Artists: Lana Del Rey": {
        "original_name": "Lana Del Rey",
        "category": "artists",
        "user_count": 4,
        "total_scrobbles": 2757,
        "shared_users": [
          "Frikomid",
          "Nubis84",
          "Rocky_stereo",
          "sdecandelario"
        ]
      },
      "Artists: The Cure": {
        "original_name": "The Cure",
        "category": "artists",
        "user_count": 4,
        "total_scrobbles": 2661,
        "shared_users": [
          "Frikomid",
          "Nubis84",
          "Rocky_stereo",
          "sdecandelario"
        ]
      },
      "Artists: Radiohead": {
        "original_name": "Radiohead",
        "category": "artists",
        "user_count": 4,
        "total_scrobbles": 2180,
        "shared_users": [
          "Frikomid",
          "Nubis84",
          "Rocky_stereo",
          "sdecandelario"
        ]
      },
      "Artists: Pink Floyd": {
        "original_name": "Pink Floyd",
        "category": "artists",
        "user_count": 4,
        "total_scrobbles": 2078,
        "shared_users": [
          "Frikomid",
          "Nubis84",
          "Rocky_stereo",
          "sdecandelario"
        ]
      },
      "Labels: [no label]": {
        "original_name": "[no label]",
        "category": "labels",
        "user_count": 4,
        "total_scrobbles": 1973,
        "shared_users": [
          "Frikomid",
          "Nubis84",
          "Rocky_stereo",
          "sdecandelario"
        ]
      }
    },
    "type": "combined"
  }
}