{
  "artists": {
    "title": "Artistas (Por Scrobbles)",
    "data": {
      "Arca": 9174,
      "Lana Del Rey": 4981,
      "Zayn": 4112,
      "Silvio Rodríguez": 3971,
      "ROSALÍA": 3918,
      "Beyoncé": 3760,
      "Taylor Swift": 3179,
      "Los Jaivas": 2985,
      "C. Tangana": 2968,
      "Talk Talk": 2633,
      "Wire": 2206,
      "The Smiths": 2140,
      "Grimes": 2069,
      "Bad Bunny": 2002,
      "Charli xcx": 1935
    },
    "total": 52033,
    "details": {
      "Arca": {
        "user_count": 3,
        "total_scrobbles": 9174,
        "shared_users": [
          "GabredMared",
          "alberto_gu",
          "sdecandelario"
        ],
        "user_plays": {},
        "artist": "",
        "album": "",
        "track": ""
      },
      "Lana Del Rey": {
        "user_count": 3,
        "total_scrobbles": 4981,
        "shared_users": [
          "GabredMared",
          "alberto_gu",
          "sdecandelario"
        ],
        "user_plays": {},
        "artist": "",
        "album": "",
        "track": ""
      },
      "Zayn": {
        "user_count": 1,
        "total_scrobbles": 4112,
        "shared_users": [
          "GabredMared"
        ],
        "user_plays": {},
        "artist": "",
        "album": "",
        "track": ""
      },
      "Silvio Rodríguez": {
        "user_count": 1,
        "total_scrobbles": 3971,
        "shared_users": [
          "GabredMared"
        ],
        "user_plays": {},
        "artist": "",
        "album": "",
        "track": ""
      },
      "ROSALÍA": {
        "user_count": 3,
        "total_scrobbles": 3918,
        "shared_users": [
          "GabredMared",
          "alberto_gu",
          "sdecandelario"
        ],
        "user_plays": {},
        "artist": "",
        "album": "",
        "track": ""
      },
      "Beyoncé": {
        "user_count": 3,
        "total_scrobbles": 3760,
        "shared_users": [
          "GabredMared",
          "alberto_gu",
          "sdecandelario"
        ],
        "user_plays": {},
        "artist": "",
        "album": "",
        "track": ""
      },
      "Taylor Swift": {
        "user_count": 3,
        "total_scrobbles": 3179,
        "shared_users": [
          "GabredMared",
          "alberto_gu",
          "sdecandelario"
        ],
        "user_plays": {},
        "artist": "",
        "album": "",
        "track": ""
      },
      "Los Jaivas": {
        "user_count": 2,
        "total_scrobbles": 2985,
        "shared_users": [
          "GabredMared",
          "sdecandelario"
        ],
        "user_plays": {},
        "artist": "",
        "album": "",
        "track": ""
      },
      "C. Tangana": {
        "user_count": 3,
        "total_scrobbles": 2968,
        "shared_users": [
          "GabredMared",
          "alberto_gu",
          "sdecandelario"
        ],
        "user_plays": {},
        "artist": "",
        "album": "",
        "track": ""
      },
      "Talk Talk": {
        "user_count": 3,
        "total_scrobbles": 2633,
        "shared_users": [
          "GabredMared",
          "alberto_gu",
          "sdecandelario"
        ],
        "user_plays": {},
        "artist": "",
        "album": "",
        "track": ""
      },
      "Wire": {
        "user_count": 3,
        "total_scrobbles": 2206,
        "shared_users": [
          "GabredMared",
          "alberto_gu",
          "sdecandelario"
        ],
        "user_plays": {},
        "artist": "",
        "album": "",
        "track": ""
      },
      "The Smiths": {
        "user_count": 3,
        "total_scrobbles": 2140,
        "shared_users": [
          "GabredMared",
          "alberto_gu",
          "sdecandelario"
        ],
        "user_plays": {},
        "artist": "",
        "album": "",
        "track": ""
      },
      "Grimes": {
        "user_count": 3,
        "total_scrobbles": 2069,
        "shared_users": [
          "GabredMared",
          "alberto_gu",
          "sdecandelario"
        ],
        "user_plays": {},
        "artist": "",
        "album": "",
        "track": ""
      },
      "Bad Bunny": {
        "user_count": 3,
        "total_scrobbles": 2002,
        "shared_users": [
          "GabredMared",
          "alberto_gu",
          "sdecandelario"
        ],
        "user_plays": {},
        "artist": "",
        "album": "",
        "track": ""
      },
      "Charli xcx": {
        "user_count": 3,
        "total_scrobbles": 1935,
        "shared_users": [
          "GabredMared",
          "alberto_gu",
          "sdecandelario"
        ],
        "user_plays": {},
        "artist": "",
        "album": "",
        "track": ""
      }
    },
    "type": "scrobbles"
  },
  "albums": {
    "title": "Álbumes (Por Scrobbles)",
    "data": {
      "Lana Del Rey - Norman Fucking Rockwell!": 2488,
      "Silvio Rodríguez - Al final de este viaje...": 2448,
      "C. Tangana - El Madrileño": 2411,
      "Arca - Arca": 2407,
      "ROSALÍA - MOTOMAMI": 2185,
      "Arca - KiCk i": 2099,
      "Los Jaivas - Los Jaivas": 2024,
      "Grimes - Art Angels": 1900,
      "Arca - KICK ii": 1880,
      "Beyoncé - Lemonade": 1869,
      "Zayn - Icarus Falls": 1806,
      "Lana Del Rey - Chemtrails Over the Country Club": 1619,
      "Beyoncé - RENAISSANCE": 1617,
      "Talk Talk - Laughing Stock": 1367,
      "Feid - FELIZ CUMPLEAÑOS FERXXO TE PIRATEAMOS EL ÁLBUM": 1225
    },
    "total": 29345,
    "details": {
      "Lana Del Rey - Norman Fucking Rockwell!": {
        "user_count": 3,
        "total_scrobbles": 2488,
        "shared_users": [
          "GabredMared",
          "alberto_gu",
          "sdecandelario"
        ],
        "user_plays": {},
        "artist": "Lana Del Rey",
        "album": "Norman Fucking Rockwell!",
        "track": ""
      },
      "Silvio Rodríguez - Al final de este viaje...": {
        "user_count": 1,
        "total_scrobbles": 2448,
        "shared_users": [
          "GabredMared"
        ],
        "user_plays": {},
        "artist": "Silvio Rodríguez",
        "album": "Al final de este viaje...",
        "track": ""
      },
      "C. Tangana - El Madrileño": {
        "user_count": 3,
        "total_scrobbles": 2411,
        "shared_users": [
          "GabredMared",
          "alberto_gu",
          "sdecandelario"
        ],
        "user_plays": {},
        "artist": "C. Tangana",
        "album": "El Madrileño",
        "track": ""
      },
      "Arca - Arca": {
        "user_count": 2,
        "total_scrobbles": 2407,
        "shared_users": [
          "GabredMared",
          "alberto_gu"
        ],
        "user_plays": {},
        "artist": "Arca",
        "album": "Arca",
        "track": ""
      },
      "ROSALÍA - MOTOMAMI": {
        "user_count": 3,
        "total_scrobbles": 2185,
        "shared_users": [
          "GabredMared",
          "alberto_gu",
          "sdecandelario"
        ],
        "user_plays": {},
        "artist": "ROSALÍA",
        "album": "MOTOMAMI",
        "track": ""
      },
      "Arca - KiCk i": {
        "user_count": 3,
        "total_scrobbles": 2099,
        "shared_users": [
          "GabredMared",
          "alberto_gu",
          "sdecandelario"
        ],
        "user_plays": {},
        "artist": "Arca",
        "album": "KiCk i",
        "track": ""
      },
      "Los Jaivas - Los Jaivas": {
        "user_count": 2,
        "total_scrobbles": 2024,
        "shared_users": [
          "GabredMared",
          "sdecandelario"
        ],
        "user_plays": {},
        "artist": "Los Jaivas",
        "album": "Los Jaivas",
        "track": ""
      },
      "Grimes - Art Angels": {
        "user_count": 1,
        "total_scrobbles": 1900,
        "shared_users": [
          "GabredMared"
        ],
        "user_plays": {},
        "artist": "Grimes",
        "album": "Art Angels",
        "track": ""
      },
      "Arca - KICK ii": {
        "user_count": 2,
        "total_scrobbles": 1880,
        "shared_users": [
          "GabredMared",
          "alberto_gu"
        ],
        "user_plays": {},
        "artist": "Arca",
        "album": "KICK ii",
        "track": ""
      },
      "Beyoncé - Lemonade": {
        "user_count": 2,
        "total_scrobbles": 1869,
        "shared_users": [
          "GabredMared",
          "alberto_gu"
        ],
        "user_plays": {},
        "artist": "Beyoncé",
        "album": "Lemonade",
        "track": ""
      },
      "Zayn - Icarus Falls": {
        "user_count": 1,
        "total_scrobbles": 1806,
        "shared_users": [
          "GabredMared"
        ],
        "user_plays": {},
        "artist": "Zayn",
        "album": "Icarus Falls",
        "track": ""
      },
      "Lana Del Rey - Chemtrails Over the Country Club": {
        "user_count": 1,
        "total_scrobbles": 1619,
        "shared_users": [
          "GabredMared"
        ],
        "user_plays": {},
        "artist": "Lana Del Rey",
        "album": "Chemtrails Over the Country Club",
        "track": ""
      },
      "Beyoncé - RENAISSANCE": {
        "user_count": 3,
        "total_scrobbles": 1617,
        "shared_users": [
          "GabredMared",
          "alberto_gu",
          "sdecandelario"
        ],
        "user_plays": {},
        "artist": "Beyoncé",
        "album": "RENAISSANCE",
        "track": ""
      },
      "Talk Talk - Laughing Stock": {
        "user_count": 2,
        "total_scrobbles": 1367,
        "shared_users": [
          "GabredMared",
          "sdecandelario"
        ],
        "user_plays": {},
        "artist": "Talk Talk",
        "album": "Laughing Stock",
        "track": ""
      },
      "Feid - FELIZ CUMPLEAÑOS FERXXO TE PIRATEAMOS EL ÁLBUM": {
        "user_count": 2,
        "total_scrobbles": 1225,
        "shared_users": [
          "GabredMared",
          "alberto_gu"
        ],
        "user_plays": {},
        "artist": "Feid",
        "album": "FELIZ CUMPLEAÑOS FERXXO TE PIRATEAMOS EL ÁLBUM",
        "track": ""
      }
    },
    "type": "scrobbles"
  },
  "tracks": {
    "title": "Canciones (Por Scrobbles)",
    "data": {
      "Arca - Machote": 905,
      "Silvio Rodríguez - Ojalá": 798,
      "Lana Del Rey - Chemtrails Over the Country Club": 681,
      "Arca - Rakata": 680,
      "Lana Del Rey - Cinnamon Girl": 671,
      "Beyoncé - ALIEN SUPERSTAR": 657,
      "Arca - Desafío": 636,
      "Arca - Tiro": 600,
      "The 1975 - Somebody Else": 574,
      "Silvio Rodríguez - Óleo de mujer con sombrero": 554,
      "Los Jaivas - En Tus Horas": 541,
      "Lana Del Rey - Tulsa Jesus Freak": 535,
      "Silvio Rodríguez - La Familia, La Propiedad Privada Y El Amor": 515,
      "Bad Gyal - Fiebre (prod. King Doudou)": 466,
      "Beyoncé - 6 Inch (feat. The Weeknd)": 435
    },
    "total": 9248,
    "details": {
      "Arca - Machote": {
        "user_count": 3,
        "total_scrobbles": 905,
        "shared_users": [
          "GabredMared",
          "alberto_gu",
          "sdecandelario"
        ],
        "user_plays": {},
        "artist": "Arca",
        "album": "",
        "track": "Machote"
      },
      "Silvio Rodríguez - Ojalá": {
        "user_count": 1,
        "total_scrobbles": 798,
        "shared_users": [
          "GabredMared"
        ],
        "user_plays": {},
        "artist": "Silvio Rodríguez",
        "album": "",
        "track": "Ojalá"
      },
      "Lana Del Rey - Chemtrails Over the Country Club": {
        "user_count": 1,
        "total_scrobbles": 681,
        "shared_users": [
          "GabredMared"
        ],
        "user_plays": {},
        "artist": "Lana Del Rey",
        "album": "",
        "track": "Chemtrails Over the Country Club"
      },
      "Arca - Rakata": {
        "user_count": 2,
        "total_scrobbles": 680,
        "shared_users": [
          "GabredMared",
          "alberto_gu"
        ],
        "user_plays": {},
        "artist": "Arca",
        "album": "",
        "track": "Rakata"
      },
      "Lana Del Rey - Cinnamon Girl": {
        "user_count": 1,
        "total_scrobbles": 671,
        "shared_users": [
          "GabredMared"
        ],
        "user_plays": {},
        "artist": "Lana Del Rey",
        "album": "",
        "track": "Cinnamon Girl"
      },
      "Beyoncé - ALIEN SUPERSTAR": {
        "user_count": 3,
        "total_scrobbles": 657,
        "shared_users": [
          "GabredMared",
          "alberto_gu",
          "sdecandelario"
        ],
        "user_plays": {},
        "artist": "Beyoncé",
        "album": "",
        "track": "ALIEN SUPERSTAR"
      },
      "Arca - Desafío": {
        "user_count": 2,
        "total_scrobbles": 636,
        "shared_users": [
          "GabredMared",
          "alberto_gu"
        ],
        "user_plays": {},
        "artist": "Arca",
        "album": "",
        "track": "Desafío"
      },
      "Arca - Tiro": {
        "user_count": 2,
        "total_scrobbles": 600,
        "shared_users": [
          "GabredMared",
          "alberto_gu"
        ],
        "user_plays": {},
        "artist": "Arca",
        "album": "",
        "track": "Tiro"
      },
      "The 1975 - Somebody Else": {
        "user_count": 1,
        "total_scrobbles": 574,
        "shared_users": [
          "GabredMared"
        ],
        "user_plays": {},
        "artist": "The 1975",
        "album": "",
        "track": "Somebody Else"
      },
      "Silvio Rodríguez - Óleo de mujer con sombrero": {
        "user_count": 1,
        "total_scrobbles": 554,
        "shared_users": [
          "GabredMared"
        ],
        "user_plays": {},
        "artist": "Silvio Rodríguez",
        "album": "",
        "track": "Óleo de mujer con sombrero"
      },
      "Los Jaivas - En Tus Horas": {
        "user_count": 2,
        "total_scrobbles": 541,
        "shared_users": [
          "GabredMared",
          "sdecandelario"
        ],
        "user_plays": {},
        "artist": "Los Jaivas",
        "album": "",
        "track": "En Tus Horas"
      },
      "Lana Del Rey - Tulsa Jesus Freak": {
        "user_count": 1,
        "total_scrobbles": 535,
        "shared_users": [
          "GabredMared"
        ],
        "user_plays": {},
        "artist": "Lana Del Rey",
        "album": "",
        "track": "Tulsa Jesus Freak"
      },
      "Silvio Rodríguez - La Familia, La Propiedad Privada Y El Amor": {
        "user_count": 1,
        "total_scrobbles": 515,
        "shared_users": [
          "GabredMared"
        ],
        "user_plays": {},
        "artist": "Silvio Rodríguez",
        "album": "",
        "track": "La Familia, La Propiedad Privada Y El Amor"
      },
      "Bad Gyal - Fiebre (prod. King Doudou)": {
        "user_count": 2,
        "total_scrobbles": 466,
        "shared_users": [
          "GabredMared",
          "alberto_gu"
        ],
        "user_plays": {},
        "artist": "Bad Gyal",
        "album": "",
        "track": "Fiebre (prod. King Doudou)"
      },
      "Beyoncé - 6 Inch (feat. The Weeknd)": {
        "user_count": 2,
        "total_scrobbles": 435,
        "shared_users": [
          "GabredMared",
          "alberto_gu"
        ],
        "user_plays": {},
        "artist": "Beyoncé",
        "album": "",
        "track": "6 Inch (feat. The Weeknd)"
      }
    },
    "type": "scrobbles"
  },
  "genres": {
    "title": "Géneros (Por Scrobbles)",
    "data": {
      "pop": 18428,
      "electronic": 12943,
      "female vocalists": 11068,
      "indie": 10481,
      "Hip-Hop": 10016,
      "indie pop": 8816,
      "post-punk": 7065,
      "folk": 6317,
      "rap": 6312,
      "latin": 6138,
      "rock": 6123,
      "punk": 5136,
      "spanish": 4322,
      "dance": 4231,
      "Progressive rock": 4230
    },
    "total": 121626,
    "details": {
      "pop": {
        "user_count": 3,
        "total_scrobbles": 18428,
        "shared_users": [
          "sdecandelario",
          "GabredMared",
          "alberto_gu"
        ],
        "user_plays": {},
        "artist": "",
        "album": "",
        "track": ""
      },
      "electronic": {
        "user_count": 3,
        "total_scrobbles": 12943,
        "shared_users": [
          "alberto_gu",
          "sdecandelario",
          "GabredMared"
        ],
        "user_plays": {},
        "artist": "",
        "album": "",
        "track": ""
      },
      "female vocalists": {
        "user_count": 3,
        "total_scrobbles": 11068,
        "shared_users": [
          "sdecandelario",
          "GabredMared",
          "alberto_gu"
        ],
        "user_plays": {},
        "artist": "",
        "album": "",
        "track": ""
      },
      "indie": {
        "user_count": 3,
        "total_scrobbles": 10481,
        "shared_users": [
          "sdecandelario",
          "GabredMared",
          "alberto_gu"
        ],
        "user_plays": {},
        "artist": "",
        "album": "",
        "track": ""
      },
      "Hip-Hop": {
        "user_count": 3,
        "total_scrobbles": 10016,
        "shared_users": [
          "alberto_gu",
          "sdecandelario",
          "GabredMared"
        ],
        "user_plays": {},
        "artist": "",
        "album": "",
        "track": ""
      },
      "indie pop": {
        "user_count": 3,
        "total_scrobbles": 8816,
        "shared_users": [
          "sdecandelario",
          "GabredMared",
          "alberto_gu"
        ],
        "user_plays": {},
        "artist": "",
        "album": "",
        "track": ""
      },
      "post-punk": {
        "user_count": 3,
        "total_scrobbles": 7065,
        "shared_users": [
          "alberto_gu",
          "sdecandelario",
          "GabredMared"
        ],
        "user_plays": {},
        "artist": "",
        "album": "",
        "track": ""
      },
      "folk": {
        "user_count": 3,
        "total_scrobbles": 6317,
        "shared_users": [
          "alberto_gu",
          "sdecandelario",
          "GabredMared"
        ],
        "user_plays": {},
        "artist": "",
        "album": "",
        "track": ""
      },
      "rap": {
        "user_count": 3,
        "total_scrobbles": 6312,
        "shared_users": [
          "sdecandelario",
          "GabredMared",
          "alberto_gu"
        ],
        "user_plays": {},
        "artist": "",
        "album": "",
        "track": ""
      },
      "latin": {
        "user_count": 3,
        "total_scrobbles": 6138,
        "shared_users": [
          "sdecandelario",
          "GabredMared",
          "alberto_gu"
        ],
        "user_plays": {},
        "artist": "",
        "album": "",
        "track": ""
      },
      "rock": {
        "user_count": 3,
        "total_scrobbles": 6123,
        "shared_users": [
          "sdecandelario",
          "GabredMared",
          "alberto_gu"
        ],
        "user_plays": {},
        "artist": "",
        "album": "",
        "track": ""
      },
      "punk": {
        "user_count": 3,
        "total_scrobbles": 5136,
        "shared_users": [
          "sdecandelario",
          "GabredMared",
          "alberto_gu"
        ],
        "user_plays": {},
        "artist": "",
        "album": "",
        "track": ""
      },
      "spanish": {
        "user_count": 3,
        "total_scrobbles": 4322,
        "shared_users": [
          "sdecandelario",
          "GabredMared",
          "alberto_gu"
        ],
        "user_plays": {},
        "artist": "",
        "album": "",
        "track": ""
      },
      "dance": {
        "user_count": 3,
        "total_scrobbles": 4231,
        "shared_users": [
          "sdecandelario",
          "GabredMared",
          "alberto_gu"
        ],
        "user_plays": {},
        "artist": "",
        "album": "",
        "track": ""
      },
      "Progressive rock": {
        "user_count": 3,
        "total_scrobbles": 4230,
        "shared_users": [
          "alberto_gu",
          "sdecandelario",
          "GabredMared"
        ],
        "user_plays": {},
        "artist": "",
        "album": "",
        "track": ""
      }
    },
    "type": "scrobbles"
  },
  "labels": {
    "title": "Sellos (Por Scrobbles)",
    "data": {
      "XL Recordings": 3097,
      "Interscope Records": 2808,
      "Movieplay": 2459,
      "4AD": 2072,
      "Columbia": 2015,
      "Capitol Records": 1606,
      "[no label]": 1551,
      "EMI": 1534,
      "Atlantic": 1503,
      "Sony Music": 1263,
      "Republic Records": 1121,
      "Warner Bros. Records": 994,
      "Boys Don’t Cry": 849,
      "RCA": 842,
      "Polydor": 800
    },
    "total": 24514,
    "details": {
      "XL Recordings": {
        "user_count": 3,
        "total_scrobbles": 3097,
        "shared_users": [
          "GabredMared",
          "alberto_gu",
          "sdecandelario"
        ],
        "user_plays": {},
        "artist": "",
        "album": "",
        "track": ""
      },
      "Interscope Records": {
        "user_count": 3,
        "total_scrobbles": 2808,
        "shared_users": [
          "GabredMared",
          "alberto_gu",
          "sdecandelario"
        ],
        "user_plays": {},
        "artist": "",
        "album": "",
        "track": ""
      },
      "Movieplay": {
        "user_count": 2,
        "total_scrobbles": 2459,
        "shared_users": [
          "GabredMared",
          "sdecandelario"
        ],
        "user_plays": {},
        "artist": "",
        "album": "",
        "track": ""
      },
      "4AD": {
        "user_count": 3,
        "total_scrobbles": 2072,
        "shared_users": [
          "GabredMared",
          "alberto_gu",
          "sdecandelario"
        ],
        "user_plays": {},
        "artist": "",
        "album": "",
        "track": ""
      },
      "Columbia": {
        "user_count": 3,
        "total_scrobbles": 2015,
        "shared_users": [
          "GabredMared",
          "alberto_gu",
          "sdecandelario"
        ],
        "user_plays": {},
        "artist": "",
        "album": "",
        "track": ""
      },
      "Capitol Records": {
        "user_count": 3,
        "total_scrobbles": 1606,
        "shared_users": [
          "GabredMared",
          "alberto_gu",
          "sdecandelario"
        ],
        "user_plays": {},
        "artist": "",
        "album": "",
        "track": ""
      },
      "[no label]": {
        "user_count": 3,
        "total_scrobbles": 1551,
        "shared_users": [
          "GabredMared",
          "alberto_gu",
          "sdecandelario"
        ],
        "user_plays": {},
        "artist": "",
        "album": "",
        "track": ""
      },
      "EMI": {
        "user_count": 3,
        "total_scrobbles": 1534,
        "shared_users": [
          "GabredMared",
          "alberto_gu",
          "sdecandelario"
        ],
        "user_plays": {},
        "artist": "",
        "album": "",
        "track": ""
      },
      "Atlantic": {
        "user_count": 3,
        "total_scrobbles": 1503,
        "shared_users": [
          "GabredMared",
          "alberto_gu",
          "sdecandelario"
        ],
        "user_plays": {},
        "artist": "",
        "album": "",
        "track": ""
      },
      "Sony Music": {
        "user_count": 3,
        "total_scrobbles": 1263,
        "shared_users": [
          "GabredMared",
          "alberto_gu",
          "sdecandelario"
        ],
        "user_plays": {},
        "artist": "",
        "album": "",
        "track": ""
      },
      "Republic Records": {
        "user_count": 3,
        "total_scrobbles": 1121,
        "shared_users": [
          "GabredMared",
          "alberto_gu",
          "sdecandelario"
        ],
        "user_plays": {},
        "artist": "",
        "album": "",
        "track": ""
      },
      "Warner Bros. Records": {
        "user_count": 3,
        "total_scrobbles": 994,
        "shared_users": [
          "GabredMared",
          "alberto_gu",
          "sdecandelario"
        ],
        "user_plays": {},
        "artist": "",
        "album": "",
        "track": ""
      },
      "Boys Don’t Cry": {
        "user_count": 3,
        "total_scrobbles": 849,
        "shared_users": [
          "GabredMared",
          "alberto_gu",
          "sdecandelario"
        ],
        "user_plays": {},
        "artist": "",
        "album": "",
        "track": ""
      },
      "RCA": {
        "user_count": 3,
        "total_scrobbles": 842,
        "shared_users": [
          "GabredMared",
          "alberto_gu",
          "sdecandelario"
        ],
        "user_plays": {},
        "artist": "",
        "album": "",
        "track": ""
      },
      "Polydor": {
        "user_count": 3,
        "total_scrobbles": 800,
        "shared_users": [
          "GabredMared",
          "alberto_gu",
          "sdecandelario"
        ],
        "user_plays": {},
        "artist": "",
        "album": "",
        "track": ""
      }
    },
    "type": "scrobbles"
  },
  "release_years": {
    "title": "Años de Lanzamiento (Por Scrobbles)",
    "data": {
      "2021": 5967,
      "2020": 5407,
      "2015": 4666,
      "2017": 4545,
      "2022": 4213,
      "2018": 3239,
      "2024": 3227,
      "2023": 3115,
      "2019": 2990,
      "1978": 2971,
      "2016": 2955,
      "2014": 2760,
      "2013": 2448,
      "2006": 1611,
      "2008": 1510
    },
    "total": 51624,
    "details": {
      "2021": {
        "user_count": 3,
        "total_scrobbles": 5967,
        "shared_users": [
          "sdecandelario",
          "GabredMared",
          "alberto_gu"
        ],
        "user_plays": {},
        "artist": "",
        "album": "",
        "track": ""
      },
      "2020": {
        "user_count": 3,
        "total_scrobbles": 5407,
        "shared_users": [
          "sdecandelario",
          "GabredMared",
          "alberto_gu"
        ],
        "user_plays": {},
        "artist": "",
        "album": "",
        "track": ""
      },
      "2015": {
        "user_count": 3,
        "total_scrobbles": 4666,
        "shared_users": [
          "sdecandelario",
          "GabredMared",
          "alberto_gu"
        ],
        "user_plays": {},
        "artist": "",
        "album": "",
        "track": ""
      },
      "2017": {
        "user_count": 3,
        "total_scrobbles": 4545,
        "shared_users": [
          "sdecandelario",
          "GabredMared",
          "alberto_gu"
        ],
        "user_plays": {},
        "artist": "",
        "album": "",
        "track": ""
      },
      "2022": {
        "user_count": 3,
        "total_scrobbles": 4213,
        "shared_users": [
          "sdecandelario",
          "GabredMared",
          "alberto_gu"
        ],
        "user_plays": {},
        "artist": "",
        "album": "",
        "track": ""
      },
      "2018": {
        "user_count": 3,
        "total_scrobbles": 3239,
        "shared_users": [
          "sdecandelario",
          "GabredMared",
          "alberto_gu"
        ],
        "user_plays": {},
        "artist": "",
        "album": "",
        "track": ""
      },
      "2024": {
        "user_count": 3,
        "total_scrobbles": 3227,
        "shared_users": [
          "sdecandelario",
          "GabredMared",
          "alberto_gu"
        ],
        "user_plays": {},
        "artist": "",
        "album": "",
        "track": ""
      },
      "2023": {
        "user_count": 3,
        "total_scrobbles": 3115,
        "shared_users": [
          "sdecandelario",
          "GabredMared",
          "alberto_gu"
        ],
        "user_plays": {},
        "artist": "",
        "album": "",
        "track": ""
      },
      "2019": {
        "user_count": 3,
        "total_scrobbles": 2990,
        "shared_users": [
          "sdecandelario",
          "GabredMared",
          "alberto_gu"
        ],
        "user_plays": {},
        "artist": "",
        "album": "",
        "track": ""
      },
      "1978": {
        "user_count": 3,
        "total_scrobbles": 2971,
        "shared_users": [
          "sdecandelario",
          "GabredMared",
          "alberto_gu"
        ],
        "user_plays": {},
        "artist": "",
        "album": "",
        "track": ""
      },
      "2016": {
        "user_count": 3,
        "total_scrobbles": 2955,
        "shared_users": [
          "sdecandelario",
          "GabredMared",
          "alberto_gu"
        ],
        "user_plays": {},
        "artist": "",
        "album": "",
        "track": ""
      },
      "2014": {
        "user_count": 3,
        "total_scrobbles": 2760,
        "shared_users": [
          "sdecandelario",
          "GabredMared",
          "alberto_gu"
        ],
        "user_plays": {},
        "artist": "",
        "album": "",
        "track": ""
      },
      "2013": {
        "user_count": 3,
        "total_scrobbles": 2448,
        "shared_users": [
          "sdecandelario",
          "GabredMared",
          "alberto_gu"
        ],
        "user_plays": {},
        "artist": "",
        "album": "",
        "track": ""
      },
      "2006": {
        "user_count": 3,
        "total_scrobbles": 1611,
        "shared_users": [
          "sdecandelario",
          "GabredMared",
          "alberto_gu"
        ],
        "user_plays": {},
        "artist": "",
        "album": "",
        "track": ""
      },
      "2008": {
        "user_count": 3,
        "total_scrobbles": 1510,
        "shared_users": [
          "sdecandelario",
          "GabredMared",
          "alberto_gu"
        ],
        "user_plays": {},
        "artist": "",
        "album": "",
        "track": ""
      }
    },
    "type": "scrobbles"
  },
  "all_combined": {
    "title": "Top 15 Global por Scrobbles",
    "data": {
      "Release_years: 2010s": 27608,
      "Release_years: 2020s+": 23301,
      "Genres: pop": 18428,
      "Genres: electronic": 12943,
      "Genres: female vocalists": 11068,
      "Release_years: 2000s": 11057,
      "Genres: indie": 10481,
      "Genres: Hip-Hop": 10016,
      "Artists: Arca": 9174,
      "Release_years: 1990s": 7860,
      "Artists: Lana Del Rey": 4981,
      "Release_years: 1980s": 4133,
      "Artists: Zayn": 4112,
      "Artists: Silvio Rodríguez": 3971,
      "Artists: ROSALÍA": 3918
    },
    "total": 163051,
    "details": {
      "Release_years: 2010s": {
        "original_name": "2010s",
        "category": "release_years",
        "user_count": 3,
        "total_scrobbles": 27608,
        "shared_users": [
          "sdecandelario",
          "GabredMared",
          "alberto_gu"
        ]
      },
      "Release_years: 2020s+": {
        "original_name": "2020s+",
        "category": "release_years",
        "user_count": 3,
        "total_scrobbles": 23301,
        "shared_users": [
          "sdecandelario",
          "GabredMared",
          "alberto_gu"
        ]
      },
      "Genres: pop": {
        "original_name": "pop",
        "category": "genres",
        "user_count": 3,
        "total_scrobbles": 18428,
        "shared_users": [
          "sdecandelario",
          "GabredMared",
          "alberto_gu"
        ]
      },
      "Genres: electronic": {
        "original_name": "electronic",
        "category": "genres",
        "user_count": 3,
        "total_scrobbles": 12943,
        "shared_users": [
          "alberto_gu",
          "sdecandelario",
          "GabredMared"
        ]
      },
      "Genres: female vocalists": {
        "original_name": "female vocalists",
        "category": "genres",
        "user_count": 3,
        "total_scrobbles": 11068,
        "shared_users": [
          "sdecandelario",
          "GabredMared",
          "alberto_gu"
        ]
      },
      "Release_years: 2000s": {
        "original_name": "2000s",
        "category": "release_years",
        "user_count": 3,
        "total_scrobbles": 11057,
        "shared_users": [
          "sdecandelario",
          "GabredMared",
          "alberto_gu"
        ]
      },
      "Genres: indie": {
        "original_name": "indie",
        "category": "genres",
        "user_count": 3,
        "total_scrobbles": 10481,
        "shared_users": [
          "sdecandelario",
          "GabredMared",
          "alberto_gu"
        ]
      },
      "Genres: Hip-Hop": {
        "original_name": "Hip-Hop",
        "category": "genres",
        "user_count": 3,
        "total_scrobbles": 10016,
        "shared_users": [
          "alberto_gu",
          "sdecandelario",
          "GabredMared"
        ]
      },
      "Artists: Arca": {
        "original_name": "Arca",
        "category": "artists",
        "user_count": 3,
        "total_scrobbles": 9174,
        "shared_users": [
          "GabredMared",
          "alberto_gu",
          "sdecandelario"
        ]
      },
      "Release_years: 1990s": {
        "original_name": "1990s",
        "category": "release_years",
        "user_count": 3,
        "total_scrobbles": 7860,
        "shared_users": [
          "sdecandelario",
          "GabredMared",
          "alberto_gu"
        ]
      },
      "Artists: Lana Del Rey": {
        "original_name": "Lana Del Rey",
        "category": "artists",
        "user_count": 3,
        "total_scrobbles": 4981,
        "shared_users": [
          "GabredMared",
          "alberto_gu",
          "sdecandelario"
        ]
      },
      "Release_years: 1980s": {
        "original_name": "1980s",
        "category": "release_years",
        "user_count": 3,
        "total_scrobbles": 4133,
        "shared_users": [
          "sdecandelario",
          "GabredMared",
          "alberto_gu"
        ]
      },
      "Artists: Zayn": {
        "original_name": "Zayn",
        "category": "artists",
        "user_count": 1,
        "total_scrobbles": 4112,
        "shared_users": [
          "GabredMared"
        ]
      },
      "Artists: Silvio Rodríguez": {
        "original_name": "Silvio Rodríguez",
        "category": "artists",
        "user_count": 1,
        "total_scrobbles": 3971,
        "shared_users": [
          "GabredMared"
        ]
      },
      "Artists: ROSALÍA": {
        "original_name": "ROSALÍA",
        "category": "artists",
        "user_count": 3,
        "total_scrobbles": 3918,
        "shared_users": [
          "GabredMared",
          "alberto_gu",
          "sdecandelario"
        ]
      }
    },
    "type": "combined"
  }
}